<!-- All the imperial banners are defined here -->
<ModOps>
    <!-- START RANTIAN LOGO BANNER -->
    <ModOp Type="addNextSibling" GUID="103115">
        <Asset>
            <Template>OrnamentalBuilding</Template>
            <Values>
                <Standard>
                    <GUID>1500030002</GUID>
                    <Name>Rantian Logo Banner</Name>
                    <IconFilename>data/ui/icon_flag_banner.png</IconFilename>
                </Standard>
                <Text>
                    <LocaText>
                        <English>
                            <Text>Rantian Logo Banner</Text>
                            <Status>Exported</Status>
                            <ExportCount>1</ExportCount>
                        </English>
                    </LocaText>
                    <LineID>36403</LineID>
                </Text>
                <Blocking>
                    <HidePropsRadius>0</HidePropsRadius>
                    <DeletePropsRadius>0</DeletePropsRadius>
                </Blocking>
                <Building>
                    <BuildingCategoryName>11149</BuildingCategoryName>
                    <AssociatedRegions>Moderate;Colony01;Africa;Mod2</AssociatedRegions>
                </Building>
                <Cost>
                    <Costs>
                        <Item>
                            <Ingredient>1010017</Ingredient>
                            <Amount>150</Amount>
                        </Item>
                        <Item>
                            <Ingredient>1010196</Ingredient>
                        </Item>
                        <Item>
                            <Ingredient>1010205</Ingredient>
                        </Item>
                        <Item>
                            <Ingredient>1010218</Ingredient>
                        </Item>
                    </Costs>
                </Cost>
                <Selection>
                    <Colors>
                        <WeakSelectionColorType>NoColor</WeakSelectionColorType>
                    </Colors>
                </Selection>
                <Object>
                    <Variations>
                        <Item>
                            <Filename>
                                data/graphics/buildings/ornamental/rantium_banner_flag_large_01.cfg</Filename>
                        </Item>
                        <Item>
                            <Filename>
                                data/graphics/buildings/ornamental/rantium_banner_flag_cobble_large_01.cfg</Filename>
                        </Item>
                        <Item>
                            <Filename>
                                data/graphics/buildings/ornamental/test/twitchdrops_advertiser_flag_01_1x1_01.cfg</Filename>
                        </Item>
                    </Variations>
                </Object>
                <Constructable />
                <Mesh />
                <SoundEmitter>
                    <DestroySounds>
                        <Item>
                            <Sound>9818756</Sound>
                        </Item>
                        <Item>
                            <VectorElement>
                                <InheritedIndex>0</InheritedIndex>
                                <InheritanceMapV2>
                                    <Entry>
                                        <TemplateName>OrnamentalBuilding</TemplateName>
                                        <Index>0</Index>
                                    </Entry>
                                </InheritanceMapV2>
                            </VectorElement>
                        </Item>
                    </DestroySounds>
                    <ConstructionSounds>
                        <BuildSuccessful>
                            <Item>
                                <VectorElement>
                                    <InheritedIndex>0</InheritedIndex>
                                    <InheritanceMapV2>
                                        <Entry>
                                            <TemplateName>OrnamentalBuilding</TemplateName>
                                            <Index>0</Index>
                                        </Entry>
                                    </InheritanceMapV2>
                                </VectorElement>
                            </Item>
                            <Item>
                                <Sound>9818759</Sound>
                            </Item>
                        </BuildSuccessful>
                        <BuildFailed>
                            <Item>
                                <Sound>9818387</Sound>
                            </Item>
                            <Item>
                                <VectorElement>
                                    <InheritedIndex>0</InheritedIndex>
                                    <InheritanceMapV2>
                                        <Entry>
                                            <TemplateName>OrnamentalBuilding</TemplateName>
                                            <Index>0</Index>
                                        </Entry>
                                    </InheritanceMapV2>
                                </VectorElement>
                            </Item>
                        </BuildFailed>
                        <BuildMoveStart>
                            <Item>
                                <Sound>9818755</Sound>
                            </Item>
                            <Item>
                                <VectorElement>
                                    <InheritedIndex>0</InheritedIndex>
                                    <InheritanceMapV2>
                                        <Entry>
                                            <TemplateName>OrnamentalBuilding</TemplateName>
                                            <Index>0</Index>
                                        </Entry>
                                    </InheritanceMapV2>
                                </VectorElement>
                            </Item>
                        </BuildMoveStart>
                    </ConstructionSounds>
                </SoundEmitter>
                <FeedbackController />
                <Ornament>
                    <PlazzaSize>1</PlazzaSize>
                    <OrnamentUnit>1</OrnamentUnit>
                    <OrnamentDescription>1500030003</OrnamentDescription>
                </Ornament>
                <Locked>
                    <DefaultLockedState>0</DefaultLockedState>
                </Locked>
                <AmbientMoodProvider />
                <Pausable />
                <Infolayer />
            </Values>
        </Asset>
    </ModOp>
    <!-- END RANTIAN LOGO BANNER -->

    <!-- START ADD RANTIAN NAVAL BANNER -->
    <ModOp Type="addNextSibling" GUID="103115">
        <Asset>
            <Template>OrnamentalBuilding</Template>
            <Values>
                <Standard>
                    <GUID>1500030004</GUID>
                    <Name>Rantian Naval Banner</Name>
                    <IconFilename>data/ui/icon_flag_banner.png</IconFilename>
                </Standard>
                <Text>
                    <LocaText>
                        <English>
                            <Text>Rantian Naval Banner</Text>
                            <Status>Exported</Status>
                            <ExportCount>1</ExportCount>
                        </English>
                    </LocaText>
                    <LineID>36403</LineID>
                </Text>
                <Blocking>
                    <HidePropsRadius>0</HidePropsRadius>
                    <DeletePropsRadius>0</DeletePropsRadius>
                </Blocking>
                <Building>
                    <BuildingCategoryName>11149</BuildingCategoryName>
                    <AssociatedRegions>Moderate;Colony01;Africa;Mod2</AssociatedRegions>
                </Building>
                <Cost>
                    <Costs>
                        <Item>
                            <Ingredient>1010017</Ingredient>
                            <Amount>150</Amount>
                        </Item>
                        <Item>
                            <Ingredient>1010196</Ingredient>
                        </Item>
                        <Item>
                            <Ingredient>1010205</Ingredient>
                        </Item>
                        <Item>
                            <Ingredient>1010218</Ingredient>
                        </Item>
                    </Costs>
                </Cost>
                <Selection>
                    <Colors>
                        <WeakSelectionColorType>NoColor</WeakSelectionColorType>
                    </Colors>
                </Selection>
                <Object>
                    <Variations>
                        <Item>
                            <Filename>
                                data/graphics/buildings/ornamental/rantium_banner_flag_large_02.cfg</Filename>
                        </Item>
                        <Item>
                            <Filename>
                                data/graphics/buildings/ornamental/rantium_banner_flag_cobble_large_02.cfg</Filename>
                        </Item>
                    </Variations>
                </Object>
                <Constructable />
                <Mesh />
                <SoundEmitter>
                    <DestroySounds>
                        <Item>
                            <Sound>9818756</Sound>
                        </Item>
                        <Item>
                            <VectorElement>
                                <InheritedIndex>0</InheritedIndex>
                                <InheritanceMapV2>
                                    <Entry>
                                        <TemplateName>OrnamentalBuilding</TemplateName>
                                        <Index>0</Index>
                                    </Entry>
                                </InheritanceMapV2>
                            </VectorElement>
                        </Item>
                    </DestroySounds>
                    <ConstructionSounds>
                        <BuildSuccessful>
                            <Item>
                                <VectorElement>
                                    <InheritedIndex>0</InheritedIndex>
                                    <InheritanceMapV2>
                                        <Entry>
                                            <TemplateName>OrnamentalBuilding</TemplateName>
                                            <Index>0</Index>
                                        </Entry>
                                    </InheritanceMapV2>
                                </VectorElement>
                            </Item>
                            <Item>
                                <Sound>9818759</Sound>
                            </Item>
                        </BuildSuccessful>
                        <BuildFailed>
                            <Item>
                                <Sound>9818387</Sound>
                            </Item>
                            <Item>
                                <VectorElement>
                                    <InheritedIndex>0</InheritedIndex>
                                    <InheritanceMapV2>
                                        <Entry>
                                            <TemplateName>OrnamentalBuilding</TemplateName>
                                            <Index>0</Index>
                                        </Entry>
                                    </InheritanceMapV2>
                                </VectorElement>
                            </Item>
                        </BuildFailed>
                        <BuildMoveStart>
                            <Item>
                                <Sound>9818755</Sound>
                            </Item>
                            <Item>
                                <VectorElement>
                                    <InheritedIndex>0</InheritedIndex>
                                    <InheritanceMapV2>
                                        <Entry>
                                            <TemplateName>OrnamentalBuilding</TemplateName>
                                            <Index>0</Index>
                                        </Entry>
                                    </InheritanceMapV2>
                                </VectorElement>
                            </Item>
                        </BuildMoveStart>
                    </ConstructionSounds>
                </SoundEmitter>
                <FeedbackController />
                <Ornament>
                    <PlazzaSize>1</PlazzaSize>
                    <OrnamentUnit>1</OrnamentUnit>
                    <OrnamentDescription>1500030005</OrnamentDescription>
                </Ornament>
                <Locked>
                    <DefaultLockedState>0</DefaultLockedState>
                </Locked>
                <AmbientMoodProvider />
                <Pausable />
                <Infolayer />
            </Values>
        </Asset>
    </ModOp>
    <!-- END ADD RANTIAN NAVAL BANNER -->

    <!-- START ADD RANIAN AIRFORCE BANNER -->
    <ModOp Type="addNextSibling" GUID="103115">
        <Asset>
            <Template>OrnamentalBuilding</Template>
            <Values>
                <Standard>
                    <GUID>1500030006</GUID>
                    <Name>Rantian Airforce Banner</Name>
                    <IconFilename>data/ui/icon_flag_banner.png</IconFilename>
                </Standard>
                <Text>
                    <LocaText>
                        <English>
                            <Text>Rantian Airforce Banner</Text>
                            <Status>Exported</Status>
                            <ExportCount>1</ExportCount>
                        </English>
                    </LocaText>
                    <LineID>36403</LineID>
                </Text>
                <Blocking>
                    <HidePropsRadius>0</HidePropsRadius>
                    <DeletePropsRadius>0</DeletePropsRadius>
                </Blocking>
                <Building>
                    <BuildingCategoryName>11149</BuildingCategoryName>
                    <AssociatedRegions>Moderate;Colony01;Africa;Mod2</AssociatedRegions>
                </Building>
                <Cost>
                    <Costs>
                        <Item>
                            <Ingredient>1010017</Ingredient>
                            <Amount>150</Amount>
                        </Item>
                        <Item>
                            <Ingredient>1010196</Ingredient>
                        </Item>
                        <Item>
                            <Ingredient>1010205</Ingredient>
                        </Item>
                        <Item>
                            <Ingredient>1010218</Ingredient>
                        </Item>
                    </Costs>
                </Cost>
                <Selection>
                    <Colors>
                        <WeakSelectionColorType>NoColor</WeakSelectionColorType>
                    </Colors>
                </Selection>
                <Object>
                    <Variations>
                        <Item>
                            <Filename>
                                data/graphics/buildings/ornamental/rantium_banner_flag_large_03.cfg</Filename>
                        </Item>
                        <Item>
                            <Filename>
                                data/graphics/buildings/ornamental/rantium_banner_flag_cobble_large_03.cfg</Filename>
                        </Item>
                    </Variations>
                </Object>
                <Constructable />
                <Mesh />
                <SoundEmitter>
                    <DestroySounds>
                        <Item>
                            <Sound>9818756</Sound>
                        </Item>
                        <Item>
                            <VectorElement>
                                <InheritedIndex>0</InheritedIndex>
                                <InheritanceMapV2>
                                    <Entry>
                                        <TemplateName>OrnamentalBuilding</TemplateName>
                                        <Index>0</Index>
                                    </Entry>
                                </InheritanceMapV2>
                            </VectorElement>
                        </Item>
                    </DestroySounds>
                    <ConstructionSounds>
                        <BuildSuccessful>
                            <Item>
                                <VectorElement>
                                    <InheritedIndex>0</InheritedIndex>
                                    <InheritanceMapV2>
                                        <Entry>
                                            <TemplateName>OrnamentalBuilding</TemplateName>
                                            <Index>0</Index>
                                        </Entry>
                                    </InheritanceMapV2>
                                </VectorElement>
                            </Item>
                            <Item>
                                <Sound>9818759</Sound>
                            </Item>
                        </BuildSuccessful>
                        <BuildFailed>
                            <Item>
                                <Sound>9818387</Sound>
                            </Item>
                            <Item>
                                <VectorElement>
                                    <InheritedIndex>0</InheritedIndex>
                                    <InheritanceMapV2>
                                        <Entry>
                                            <TemplateName>OrnamentalBuilding</TemplateName>
                                            <Index>0</Index>
                                        </Entry>
                                    </InheritanceMapV2>
                                </VectorElement>
                            </Item>
                        </BuildFailed>
                        <BuildMoveStart>
                            <Item>
                                <Sound>9818755</Sound>
                            </Item>
                            <Item>
                                <VectorElement>
                                    <InheritedIndex>0</InheritedIndex>
                                    <InheritanceMapV2>
                                        <Entry>
                                            <TemplateName>OrnamentalBuilding</TemplateName>
                                            <Index>0</Index>
                                        </Entry>
                                    </InheritanceMapV2>
                                </VectorElement>
                            </Item>
                        </BuildMoveStart>
                    </ConstructionSounds>
                </SoundEmitter>
                <FeedbackController />
                <Ornament>
                    <PlazzaSize>1</PlazzaSize>
                    <OrnamentUnit>1</OrnamentUnit>
                    <OrnamentDescription>1500030007</OrnamentDescription>
                </Ornament>
                <Locked>
                    <DefaultLockedState>0</DefaultLockedState>
                </Locked>
                <AmbientMoodProvider />
                <Pausable />
                <Infolayer />
            </Values>
        </Asset>
    </ModOp>
    <!-- END ADD RANIAN AIRFORCE BANNER -->

    <!-- START RANTIAN IMPERIUM BANNER -->
    <ModOp Type="addNextSibling" GUID="103115">
        <Asset>
            <Template>OrnamentalBuilding</Template>
            <Values>
                <Standard>
                    <GUID>1500030008</GUID>
                    <Name>Rantian Imperium Banner</Name>
                    <IconFilename>data/ui/icon_flag_banner.png</IconFilename>
                </Standard>
                <Text>
                    <LocaText>
                        <English>
                            <Text>Rantian Imperium Banner</Text>
                            <Status>Exported</Status>
                            <ExportCount>1</ExportCount>
                        </English>
                    </LocaText>
                    <LineID>36403</LineID>
                </Text>
                <Blocking>
                    <HidePropsRadius>0</HidePropsRadius>
                    <DeletePropsRadius>0</DeletePropsRadius>
                </Blocking>
                <Building>
                    <BuildingCategoryName>11149</BuildingCategoryName>
                    <AssociatedRegions>Moderate;Colony01;Africa;Mod2</AssociatedRegions>
                </Building>
                <Cost>
                    <Costs>
                        <Item>
                            <Ingredient>1010017</Ingredient>
                            <Amount>150</Amount>
                        </Item>
                        <Item>
                            <Ingredient>1010196</Ingredient>
                        </Item>
                        <Item>
                            <Ingredient>1010205</Ingredient>
                        </Item>
                        <Item>
                            <Ingredient>1010218</Ingredient>
                        </Item>
                    </Costs>
                </Cost>
                <Selection>
                    <Colors>
                        <WeakSelectionColorType>NoColor</WeakSelectionColorType>
                    </Colors>
                </Selection>
                <Object>
                    <Variations>
                        <Item>
                            <Filename>
                                data/graphics/buildings/ornamental/rantium_banner_flag_large_04.cfg</Filename>
                        </Item>
                        <Item>
                            <Filename>
                                data/graphics/buildings/ornamental/rantium_banner_flag_cobble_large_04.cfg</Filename>
                        </Item>
                    </Variations>
                </Object>
                <Constructable />
                <Mesh />
                <SoundEmitter>
                    <DestroySounds>
                        <Item>
                            <Sound>9818756</Sound>
                        </Item>
                        <Item>
                            <VectorElement>
                                <InheritedIndex>0</InheritedIndex>
                                <InheritanceMapV2>
                                    <Entry>
                                        <TemplateName>OrnamentalBuilding</TemplateName>
                                        <Index>0</Index>
                                    </Entry>
                                </InheritanceMapV2>
                            </VectorElement>
                        </Item>
                    </DestroySounds>
                    <ConstructionSounds>
                        <BuildSuccessful>
                            <Item>
                                <VectorElement>
                                    <InheritedIndex>0</InheritedIndex>
                                    <InheritanceMapV2>
                                        <Entry>
                                            <TemplateName>OrnamentalBuilding</TemplateName>
                                            <Index>0</Index>
                                        </Entry>
                                    </InheritanceMapV2>
                                </VectorElement>
                            </Item>
                            <Item>
                                <Sound>9818759</Sound>
                            </Item>
                        </BuildSuccessful>
                        <BuildFailed>
                            <Item>
                                <Sound>9818387</Sound>
                            </Item>
                            <Item>
                                <VectorElement>
                                    <InheritedIndex>0</InheritedIndex>
                                    <InheritanceMapV2>
                                        <Entry>
                                            <TemplateName>OrnamentalBuilding</TemplateName>
                                            <Index>0</Index>
                                        </Entry>
                                    </InheritanceMapV2>
                                </VectorElement>
                            </Item>
                        </BuildFailed>
                        <BuildMoveStart>
                            <Item>
                                <Sound>9818755</Sound>
                            </Item>
                            <Item>
                                <VectorElement>
                                    <InheritedIndex>0</InheritedIndex>
                                    <InheritanceMapV2>
                                        <Entry>
                                            <TemplateName>OrnamentalBuilding</TemplateName>
                                            <Index>0</Index>
                                        </Entry>
                                    </InheritanceMapV2>
                                </VectorElement>
                            </Item>
                        </BuildMoveStart>
                    </ConstructionSounds>
                </SoundEmitter>
                <FeedbackController />
                <Ornament>
                    <PlazzaSize>1</PlazzaSize>
                    <OrnamentUnit>1</OrnamentUnit>
                    <OrnamentDescription>1500030009</OrnamentDescription>
                </Ornament>
                <Locked>
                    <DefaultLockedState>0</DefaultLockedState>
                </Locked>
                <AmbientMoodProvider />
                <Pausable />
                <Infolayer />
            </Values>
        </Asset>
    </ModOp>
    <!-- END RANTIAN IMPERIUM BANNER -->

    <!-- START RANTIAN IMPERIUM LAND OF LIONS BANNER -->
    <ModOp Type="addNextSibling" GUID="103115">
        <Asset>
            <Template>OrnamentalBuilding</Template>
            <Values>
                <Standard>
                    <GUID>1500030010</GUID>
                    <Name>Rantian Imperium Land of Lions Banner</Name>
                    <IconFilename>data/ui/icon_flag_banner.png</IconFilename>
                </Standard>
                <Text>
                    <LocaText>
                        <English>
                            <Text>Rantian Imperium Land of Lions Banner</Text>
                            <Status>Exported</Status>
                            <ExportCount>1</ExportCount>
                        </English>
                    </LocaText>
                    <LineID>36403</LineID>
                </Text>
                <Blocking>
                    <HidePropsRadius>0</HidePropsRadius>
                    <DeletePropsRadius>0</DeletePropsRadius>
                </Blocking>
                <Building>
                    <BuildingCategoryName>11149</BuildingCategoryName>
                    <AssociatedRegions>Moderate;Colony01;Africa;Mod2</AssociatedRegions>
                </Building>
                <Cost>
                    <Costs>
                        <Item>
                            <Ingredient>1010017</Ingredient>
                            <Amount>150</Amount>
                        </Item>
                        <Item>
                            <Ingredient>1010196</Ingredient>
                        </Item>
                        <Item>
                            <Ingredient>1010205</Ingredient>
                        </Item>
                        <Item>
                            <Ingredient>1010218</Ingredient>
                        </Item>
                    </Costs>
                </Cost>
                <Selection>
                    <Colors>
                        <WeakSelectionColorType>NoColor</WeakSelectionColorType>
                    </Colors>
                </Selection>
                <Object>
                    <Variations>
                        <Item>
                            <Filename>
                                data/graphics/buildings/ornamental/rantium_banner_flag_large_05.cfg</Filename>
                        </Item>
                        <Item>
                            <Filename>
                                data/graphics/buildings/ornamental/rantium_banner_flag_cobble_large_05.cfg</Filename>
                        </Item>
                    </Variations>
                </Object>
                <Constructable />
                <Mesh />
                <SoundEmitter>
                    <DestroySounds>
                        <Item>
                            <Sound>9818756</Sound>
                        </Item>
                        <Item>
                            <VectorElement>
                                <InheritedIndex>0</InheritedIndex>
                                <InheritanceMapV2>
                                    <Entry>
                                        <TemplateName>OrnamentalBuilding</TemplateName>
                                        <Index>0</Index>
                                    </Entry>
                                </InheritanceMapV2>
                            </VectorElement>
                        </Item>
                    </DestroySounds>
                    <ConstructionSounds>
                        <BuildSuccessful>
                            <Item>
                                <VectorElement>
                                    <InheritedIndex>0</InheritedIndex>
                                    <InheritanceMapV2>
                                        <Entry>
                                            <TemplateName>OrnamentalBuilding</TemplateName>
                                            <Index>0</Index>
                                        </Entry>
                                    </InheritanceMapV2>
                                </VectorElement>
                            </Item>
                            <Item>
                                <Sound>9818759</Sound>
                            </Item>
                        </BuildSuccessful>
                        <BuildFailed>
                            <Item>
                                <Sound>9818387</Sound>
                            </Item>
                            <Item>
                                <VectorElement>
                                    <InheritedIndex>0</InheritedIndex>
                                    <InheritanceMapV2>
                                        <Entry>
                                            <TemplateName>OrnamentalBuilding</TemplateName>
                                            <Index>0</Index>
                                        </Entry>
                                    </InheritanceMapV2>
                                </VectorElement>
                            </Item>
                        </BuildFailed>
                        <BuildMoveStart>
                            <Item>
                                <Sound>9818755</Sound>
                            </Item>
                            <Item>
                                <VectorElement>
                                    <InheritedIndex>0</InheritedIndex>
                                    <InheritanceMapV2>
                                        <Entry>
                                            <TemplateName>OrnamentalBuilding</TemplateName>
                                            <Index>0</Index>
                                        </Entry>
                                    </InheritanceMapV2>
                                </VectorElement>
                            </Item>
                        </BuildMoveStart>
                    </ConstructionSounds>
                </SoundEmitter>
                <FeedbackController />
                <Ornament>
                    <PlazzaSize>1</PlazzaSize>
                    <OrnamentUnit>1</OrnamentUnit>
                    <OrnamentDescription>1500030011</OrnamentDescription>
                </Ornament>
                <Locked>
                    <DefaultLockedState>0</DefaultLockedState>
                </Locked>
                <AmbientMoodProvider />
                <Pausable />
                <Infolayer />
            </Values>
        </Asset>
    </ModOp>
    <!-- END RANTIAN IMPERIUM LAND OF LIONS BANNER -->
</ModOps>